odoo/addons/account_invoice_section_sale_order/README.rst
odoo/addons/account_invoice_section_sale_order/__init__.py
odoo/addons/account_invoice_section_sale_order/__manifest__.py
odoo/addons/account_invoice_section_sale_order/i18n/account_invoice_section_sale_order.pot
odoo/addons/account_invoice_section_sale_order/i18n/es.po
odoo/addons/account_invoice_section_sale_order/models/__init__.py
odoo/addons/account_invoice_section_sale_order/models/sale_order.py
odoo/addons/account_invoice_section_sale_order/readme/CONTRIBUTORS.rst
odoo/addons/account_invoice_section_sale_order/readme/DESCRIPTION.rst
odoo/addons/account_invoice_section_sale_order/static/description/icon.png
odoo/addons/account_invoice_section_sale_order/static/description/index.html
odoo/addons/account_invoice_section_sale_order/tests/__init__.py
odoo/addons/account_invoice_section_sale_order/tests/test_invoice_group_by_sale_order.py
odoo13_addon_account_invoice_section_sale_order-13.0.1.1.0.dist-info/METADATA
odoo13_addon_account_invoice_section_sale_order-13.0.1.1.0.dist-info/WHEEL
odoo13_addon_account_invoice_section_sale_order-13.0.1.1.0.dist-info/top_level.txt
odoo13_addon_account_invoice_section_sale_order-13.0.1.1.0.dist-info/RECORD
